testcato/__init__.py
testcato/ai_agent.py
testcato/categorizer.py
testcato/conftest.py
testcato/llm_providers.py
testcato/pytest_testcato.py
testcato-1.2.5.dist-info/LICENSE
testcato-1.2.5.dist-info/METADATA
testcato-1.2.5.dist-info/WHEEL
testcato-1.2.5.dist-info/entry_points.txt
testcato-1.2.5.dist-info/top_level.txt
testcato-1.2.5.dist-info/RECORD
