Metadata-Version: 2.1
Name: testcato
Version: 1.2.5
Summary: A package for categorizing test results.
Author: Anurag
Author-email: anuragsinha003@gmail.com
License: MIT
License-File: LICENSE
